[
  {
    "title": "ニュースができました",
    "description": "最新中身はこんな感じです。",
    "date": "2022-12-23T11:22:00.009Z"
  },
  {
    "title": "1ニュースができました",
    "description": "2番目中身はこんな感じです。",
    "date": "2022-12-22T11:22:00.009Z"
  },
  {
    "title": "2ニュースができました",
    "description": "3番目中身はこんな感じです。",
    "date": "2022-12-21T11:22:00.009Z"
  },
  {
    "title": "55ニュースができました",
    "description": "4中身はこんな感じです。",
    "date": "2022-11-23T11:22:00.009Z"
  },
  {
    "title": "新しいニュースのタイトルは……",
    "date": "2040-09-30T15:00:00.000Z",
    "description": "こんな感じでニュースを追加できるようになりました。今後ともよろしくお願いします。"
  }
]